<?xml version="1.0" encoding="utf-8"?>
<!DOCTYPE Map[]>
<Map srs="+proj=merc +a=6378137 +b=6378137 +lat_ts=0.0 +lon_0=0.0 +x_0=0.0 +y_0=0.0 +k=1.0 +units=m +nadgrids=@null +wktext +no_defs +over">

<Parameters>
  <Parameter name="bounds">-180,-85.0511,180,85.0511</Parameter>
  <Parameter name="center">-96.6797,38.3417,3</Parameter>
  <Parameter name="format">png8:m=h</Parameter>
  <Parameter name="maxzoom">6</Parameter>
  <Parameter name="minzoom">0</Parameter>
  <Parameter name="source"><![CDATA[tmsource:///Users/dan/Documents/mapping-future/layers/pipeplines-oil.tm2source]]></Parameter>
</Parameters>


<Style name="CrudeOil_Pipelines_US_Nov2014" filter-mode="first">
  <Rule>
    <LineSymbolizer stroke-width="1" stroke="#e80c7a" />
  </Rule>
</Style>
<Layer name="CrudeOil_Pipelines_US_Nov2014"
  srs="+proj=merc +a=6378137 +b=6378137 +lat_ts=0.0 +lon_0=0.0 +x_0=0.0 +y_0=0.0 +k=1.0 +units=m +nadgrids=@null +wktext +no_defs +over">
    <StyleName>CrudeOil_Pipelines_US_Nov2014</StyleName>  </Layer>

</Map>